metarepo/__init__.py
metarepo/cli.py
metarepo/cli_decorators.py
metarepo/commands/__init__.py
metarepo/commands/init_cmd.py
metarepo/commands/list_cmd.py
metarepo/commands/status_cmd.py
metarepo/commands/sync_cmd.py
metarepo/manifest.py
metarepo/ui.py
metarepo/vcs_git.py
metarepo-0.1.2.dist-info/entry_points.txt
metarepo-0.1.2.dist-info/WHEEL
metarepo-0.1.2.dist-info/METADATA
metarepo-0.1.2.dist-info/RECORD
