Metadata-Version: 2.1
Name: metarepo
Version: 0.1.2
Summary: Git Meta Repository Manager
License: MIT
Keywords: git,repository,repo,submodules
Author: Jim Ekman
Author-email: jim@nurd.se
Requires-Python: >=3.6.1,<4.0.0
Classifier: Development Status :: 4 - Beta
Classifier: Environment :: Console
Classifier: Intended Audience :: Developers
Classifier: License :: OSI Approved :: MIT License
Classifier: Natural Language :: English
Classifier: Programming Language :: Python :: 3
Classifier: Programming Language :: Python :: 3.6
Classifier: Programming Language :: Python :: 3.7
Classifier: Programming Language :: Python :: 3.8
Classifier: Programming Language :: Python :: 3.9
Classifier: Topic :: Software Development :: Version Control
Classifier: Topic :: Software Development :: Version Control :: Git
Requires-Dist: click (>=7.1.1,<8.0.0)
Requires-Dist: colorama (>=0.4.3,<0.5.0)
Requires-Dist: gitpython (>=3.1.0,<4.0.0)
Requires-Dist: prompt-toolkit (>=3.0.7,<4.0.0)
Requires-Dist: pydantic (>=1.6.1,<2.0.0)
Requires-Dist: pyyaml (>=5.3.1,<6.0.0)
